emtracks/Bdist.py
emtracks/__init__.py
emtracks/conversions.py
emtracks/generate_momentum.py
emtracks/helix.py
emtracks/impact_param.py
emtracks/interpolations.py
emtracks/mapinterp.py
emtracks/particle.py
emtracks/plotting.py
emtracks/tools.py
emtracks-0.0.0.dist-info/LICENSE
emtracks-0.0.0.dist-info/METADATA
emtracks-0.0.0.dist-info/WHEEL
emtracks-0.0.0.dist-info/top_level.txt
emtracks-0.0.0.dist-info/RECORD
